planer/__init__.py
planer/io.py
planer/layer.py
planer/net.py
planer/util.py
planer-0.35.dist-info/LICENSE
planer-0.35.dist-info/METADATA
planer-0.35.dist-info/WHEEL
planer-0.35.dist-info/top_level.txt
planer-0.35.dist-info/RECORD
