Metadata-Version: 2.1
Name: planer
Version: 0.35
Summary: Powerful Light Artificial NEuRon
Home-page: https://github.com/Image-Py/planer
Author: Y.Dong, YXDragon
Author-email: yxdragon@imagepy.org
License: BSD 3-clause
Platform: UNKNOWN
Requires-Dist: numpy
